mcp_server/README.md
mcp_server/__init__.py
mcp_server/__main__.py
mcp_server/config.py
mcp_server/server.py
mcp_server/database/__init__.py
mcp_server/database/allowed_views.py
mcp_server/database/connection.py
mcp_server/database/query_executor.py
mcp_server/prompts/__init__.py
mcp_server/prompts/analysis_guide.py
mcp_server/resources/__init__.py
mcp_server/resources/context.py
mcp_server/resources/reference.py
mcp_server/resources/schema.py
mcp_server/resources/stats.py
mcp_server/tools/__init__.py
mcp_server/tools/query.py
mcp_server/utils/__init__.py
mcp_server/utils/audit.py
mcp_server/utils/errors.py
mcp_server/utils/logging.py
ecs_contract_mcp-0.1.2.dist-info/METADATA
ecs_contract_mcp-0.1.2.dist-info/WHEEL
ecs_contract_mcp-0.1.2.dist-info/entry_points.txt
ecs_contract_mcp-0.1.2.dist-info/RECORD
