Metadata-Version: 2.4
Name: ecs-contract-mcp
Version: 0.1.2
Summary: ECS Contract Management MCP Server
Requires-Python: >=3.11
Requires-Dist: mcp<2.0.0,>=1.0.0
Requires-Dist: pydantic-settings>=2.0.0
Requires-Dist: pydantic<3.0.0,>=2.0.0
Requires-Dist: pyodbc>=5.2.0
Requires-Dist: structlog>=24.0.0
Provides-Extra: dev
Requires-Dist: mypy>=1.10.0; extra == 'dev'
Requires-Dist: pytest-asyncio>=0.23.0; extra == 'dev'
Requires-Dist: pytest>=8.0.0; extra == 'dev'
Requires-Dist: ruff>=0.4.0; extra == 'dev'
